{
  "firstLayout": "",
  "gdVersion": {
    "build": 217,
    "major": 5,
    "minor": 4,
    "revision": 0
  },
  "properties": {
    "adaptGameResolutionAtRuntime": true,
    "antialiasingMode": "MSAA",
    "antialisingEnabledOnMobile": false,
    "folderProject": false,
    "orientation": "landscape",
    "packageName": "com.example.gamename",
    "pixelsRounding": false,
    "projectUuid": "35fa5477-4873-4d13-a4da-95b213e03ff8",
    "scaleMode": "linear",
    "sizeOnStartupMode": "adaptWidth",
    "templateSlug": "",
    "useExternalSourceFiles": false,
    "version": "1.0.0",
    "name": "Santa's Workshop",
    "description": "",
    "author": "",
    "windowWidth": 1280,
    "windowHeight": 720,
    "latestCompilationDirectory": "",
    "maxFPS": 60,
    "minFPS": 20,
    "verticalSync": false,
    "platformSpecificAssets": {},
    "loadingScreen": {
      "backgroundColor": 0,
      "backgroundFadeInDuration": 0.2,
      "backgroundImageResourceName": "",
      "gdevelopLogoStyle": "light",
      "logoAndProgressFadeInDuration": 0.2,
      "logoAndProgressLogoFadeInDelay": 0,
      "minDuration": 1.5,
      "progressBarColor": 16777215,
      "progressBarHeight": 20,
      "progressBarMaxWidth": 200,
      "progressBarMinWidth": 40,
      "progressBarWidthPercent": 30,
      "showGDevelopSplash": true,
      "showProgressBar": true
    },
    "watermark": {
      "placement": "bottom-left",
      "showWatermark": true
    },
    "authorIds": [],
    "authorUsernames": [],
    "categories": [],
    "playableDevices": [],
    "extensionProperties": [],
    "platforms": [
      {
        "name": "GDevelop JS platform"
      }
    ],
    "currentPlatform": "GDevelop JS platform"
  },
  "resources": {
    "resources": [
      {
        "alwaysLoaded": false,
        "file": "TUFF.png",
        "kind": "image",
        "metadata": "",
        "name": "TUFF.png",
        "smoothed": true,
        "userAdded": false
      },
      {
        "alwaysLoaded": false,
        "file": "images.jpg",
        "kind": "image",
        "metadata": "",
        "name": "images.jpg",
        "smoothed": true,
        "userAdded": false
      },
      {
        "alwaysLoaded": false,
        "file": "bu2041bk-1-main-isb.webp",
        "kind": "image",
        "metadata": "",
        "name": "bu2041bk-1-main-isb.webp",
        "smoothed": true,
        "userAdded": false
      },
      {
        "alwaysLoaded": false,
        "file": "81U7rrsM8zL.jpg",
        "kind": "image",
        "metadata": "",
        "name": "81U7rrsM8zL.jpg",
        "smoothed": true,
        "userAdded": false
      },
      {
        "alwaysLoaded": false,
        "file": "8-x-8-Microfiber-Silk-Lens-Cloth-Blue_1200x600_crop_center.webp",
        "kind": "image",
        "metadata": "",
        "name": "8-x-8-Microfiber-Silk-Lens-Cloth-Blue_1200x600_crop_center.webp",
        "smoothed": true,
        "userAdded": false
      },
      {
        "alwaysLoaded": false,
        "file": "images2.jpg",
        "kind": "image",
        "metadata": "",
        "name": "images2.jpg",
        "smoothed": true,
        "userAdded": false
      },
      {
        "alwaysLoaded": false,
        "file": "34230700232069x20042065.jpg",
        "kind": "image",
        "metadata": "",
        "name": "34230700232069x20042065.jpg",
        "smoothed": true,
        "userAdded": false
      },
      {
        "alwaysLoaded": false,
        "file": "assets/NewSprite2.png",
        "kind": "image",
        "metadata": "{\"extension\":\".png\"}",
        "name": "NewSprite2",
        "smoothed": true,
        "userAdded": false
      },
      {
        "alwaysLoaded": false,
        "file": "59281_W3.jpg",
        "kind": "image",
        "metadata": "",
        "name": "59281_W3.jpg",
        "smoothed": true,
        "userAdded": false
      },
      {
        "alwaysLoaded": false,
        "file": "Crafting_Table_JE4_BE3.webp",
        "kind": "image",
        "metadata": "",
        "name": "Crafting_Table_JE4_BE3.webp",
        "smoothed": true,
        "userAdded": false
      },
      {
        "alwaysLoaded": false,
        "file": "assets/Invisible_Saw_barrier_A.png",
        "kind": "image",
        "metadata": "{\"extension\":\".png\"}",
        "name": "Invisible_Saw_barrier_A",
        "smoothed": true,
        "userAdded": false
      },
      {
        "alwaysLoaded": false,
        "file": "assets/Invisible_Saw_Barrier_B.png",
        "kind": "image",
        "metadata": "{\"extension\":\".png\"}",
        "name": "Invisible_Saw_Barrier_B",
        "smoothed": true,
        "userAdded": false
      },
      {
        "alwaysLoaded": false,
        "file": "images3.jpg",
        "kind": "image",
        "metadata": "",
        "name": "images3.jpg",
        "smoothed": true,
        "userAdded": false
      },
      {
        "alwaysLoaded": false,
        "file": "assets/NewTiledSprite.png",
        "kind": "image",
        "metadata": "{\"extension\":\".png\",\"pskl\":{}}",
        "name": "NewTiledSprite",
        "smoothed": true,
        "userAdded": false
      },
      {
        "alwaysLoaded": false,
        "file": "assets/NewSprite.png",
        "kind": "image",
        "metadata": "{\"extension\":\".png\"}",
        "name": "NewSprite",
        "smoothed": true,
        "userAdded": false
      },
      {
        "alwaysLoaded": false,
        "file": "assets/NewSprite3.png",
        "kind": "image",
        "metadata": "{\"extension\":\".png\"}",
        "name": "NewSprite3",
        "smoothed": true,
        "userAdded": false
      },
      {
        "alwaysLoaded": false,
        "file": "assets/Bun_Spinning_1.png",
        "kind": "image",
        "metadata": "",
        "name": "Bun_Spinning_1.png",
        "smoothed": false,
        "userAdded": false,
        "origin": {
          "identifier": "https://asset-resources.gdevelop.io/public-resources/16x16 Pixel art spinning Items/fcba78cb96bdfc824107d4857b7c4e9a6409b21a047f63289975273c22028b44_Bun_Spinning_1.png",
          "name": "Bun_Spinning_1.png"
        }
      },
      {
        "alwaysLoaded": false,
        "file": "assets/Bun_Spinning_2.png",
        "kind": "image",
        "metadata": "",
        "name": "Bun_Spinning_2.png",
        "smoothed": false,
        "userAdded": false,
        "origin": {
          "identifier": "https://asset-resources.gdevelop.io/public-resources/16x16 Pixel art spinning Items/d398d6888781fcd1eeb7b917804f67898f5bcb2ffe2598276c863a5fec8eb84c_Bun_Spinning_2.png",
          "name": "Bun_Spinning_2.png"
        }
      },
      {
        "alwaysLoaded": false,
        "file": "assets/Bun_Spinning_3.png",
        "kind": "image",
        "metadata": "",
        "name": "Bun_Spinning_3.png",
        "smoothed": false,
        "userAdded": false,
        "origin": {
          "identifier": "https://asset-resources.gdevelop.io/public-resources/16x16 Pixel art spinning Items/e769eb35f311f4fa2019f2ce3374227ea406e9c06f7f085e64e30a41fc6d34df_Bun_Spinning_3.png",
          "name": "Bun_Spinning_3.png"
        }
      },
      {
        "alwaysLoaded": false,
        "file": "assets/Bun_Spinning_4.png",
        "kind": "image",
        "metadata": "",
        "name": "Bun_Spinning_4.png",
        "smoothed": false,
        "userAdded": false,
        "origin": {
          "identifier": "https://asset-resources.gdevelop.io/public-resources/16x16 Pixel art spinning Items/007c25d5ba119edf08eef2a3dd7d322785abf8cdb386aa64a5ee768765a6f727_Bun_Spinning_4.png",
          "name": "Bun_Spinning_4.png"
        }
      },
      {
        "alwaysLoaded": false,
        "file": "assets/Bun_Spinning_5.png",
        "kind": "image",
        "metadata": "",
        "name": "Bun_Spinning_5.png",
        "smoothed": false,
        "userAdded": false,
        "origin": {
          "identifier": "https://asset-resources.gdevelop.io/public-resources/16x16 Pixel art spinning Items/605f6d03d2819edc5383708d030ba743cf8dc20f44ecf0107f1e567b8f0dc34d_Bun_Spinning_5.png",
          "name": "Bun_Spinning_5.png"
        }
      },
      {
        "alwaysLoaded": false,
        "file": "assets/Bun_Spinning_6.png",
        "kind": "image",
        "metadata": "",
        "name": "Bun_Spinning_6.png",
        "smoothed": false,
        "userAdded": false,
        "origin": {
          "identifier": "https://asset-resources.gdevelop.io/public-resources/16x16 Pixel art spinning Items/aa9d72e6aff63c5a193d3d3c7c2a9c925dea6af5ff14d77816f6cd6861cf653a_Bun_Spinning_6.png",
          "name": "Bun_Spinning_6.png"
        }
      },
      {
        "alwaysLoaded": false,
        "file": "assets/Bun_Spinning_7.png",
        "kind": "image",
        "metadata": "",
        "name": "Bun_Spinning_7.png",
        "smoothed": false,
        "userAdded": false,
        "origin": {
          "identifier": "https://asset-resources.gdevelop.io/public-resources/16x16 Pixel art spinning Items/457eb86b2dcf5bfad81ab5c2cfaf4558a3b7226200936e916a8a42554354fc9c_Bun_Spinning_7.png",
          "name": "Bun_Spinning_7.png"
        }
      },
      {
        "alwaysLoaded": false,
        "file": "assets/Bun_Spinning_8.png",
        "kind": "image",
        "metadata": "",
        "name": "Bun_Spinning_8.png",
        "smoothed": false,
        "userAdded": false,
        "origin": {
          "identifier": "https://asset-resources.gdevelop.io/public-resources/16x16 Pixel art spinning Items/e8a71965c3312a101e25d89aceb39c64d7e86873ab4f97d447c9e4fcf9f1cb3f_Bun_Spinning_8.png",
          "name": "Bun_Spinning_8.png"
        }
      },
      {
        "alwaysLoaded": false,
        "file": "assets/9patch_Wood Background_all_64.png",
        "kind": "image",
        "metadata": "",
        "name": "9patch_Wood Background_all_64.png",
        "smoothed": false,
        "userAdded": false,
        "origin": {
          "identifier": "https://asset-resources.gdevelop.io/public-resources/Pirate Bomb Pack/Tile Sets/Wood Background/cde7121802cd226997240e3941fbaf9193a225e5ffff40cc849e918047959711_9patch_Wood Background_all_64.png",
          "name": "9patch_Wood Background_all_64.png"
        }
      },
      {
        "alwaysLoaded": false,
        "file": "assets/Saw_Off.png",
        "kind": "image",
        "metadata": "",
        "name": "Saw_Off.png",
        "smoothed": false,
        "userAdded": false,
        "origin": {
          "identifier": "https://asset-resources.gdevelop.io/public-resources/Pixel Adventure Pack/Traps/Saw/8215537950e4e02640f87df890132c2d9c19c42dbaf5d0cc8237272112941978_Saw_Off.png",
          "name": "Saw_Off.png"
        }
      },
      {
        "alwaysLoaded": false,
        "file": "assets/Saw_On_1.png",
        "kind": "image",
        "metadata": "",
        "name": "Saw_On_1.png",
        "smoothed": false,
        "userAdded": false,
        "origin": {
          "identifier": "https://asset-resources.gdevelop.io/public-resources/Pixel Adventure Pack/Traps/Saw/8215537950e4e02640f87df890132c2d9c19c42dbaf5d0cc8237272112941978_Saw_On_1.png",
          "name": "Saw_On_1.png"
        }
      },
      {
        "alwaysLoaded": false,
        "file": "assets/Saw_On_2.png",
        "kind": "image",
        "metadata": "",
        "name": "Saw_On_2.png",
        "smoothed": false,
        "userAdded": false,
        "origin": {
          "identifier": "https://asset-resources.gdevelop.io/public-resources/Pixel Adventure Pack/Traps/Saw/1d982f3e006a7ac6b76bca8cefbf716fd017b25f7e0218942276b4dd92ac1813_Saw_On_2.png",
          "name": "Saw_On_2.png"
        }
      },
      {
        "alwaysLoaded": false,
        "file": "assets/Saw_On_3.png",
        "kind": "image",
        "metadata": "",
        "name": "Saw_On_3.png",
        "smoothed": false,
        "userAdded": false,
        "origin": {
          "identifier": "https://asset-resources.gdevelop.io/public-resources/Pixel Adventure Pack/Traps/Saw/b208726b0292bb1f401f3738902ec190c004841ae8c555b2817d9f19ef46ca62_Saw_On_3.png",
          "name": "Saw_On_3.png"
        }
      },
      {
        "alwaysLoaded": false,
        "file": "assets/Saw_On_4.png",
        "kind": "image",
        "metadata": "",
        "name": "Saw_On_4.png",
        "smoothed": false,
        "userAdded": false,
        "origin": {
          "identifier": "https://asset-resources.gdevelop.io/public-resources/Pixel Adventure Pack/Traps/Saw/b6119060081879814ea630f152a39fb3c303d421b797515814c045b73b94abdf_Saw_On_4.png",
          "name": "Saw_On_4.png"
        }
      },
      {
        "alwaysLoaded": false,
        "file": "assets/Saw_On_5.png",
        "kind": "image",
        "metadata": "",
        "name": "Saw_On_5.png",
        "smoothed": false,
        "userAdded": false,
        "origin": {
          "identifier": "https://asset-resources.gdevelop.io/public-resources/Pixel Adventure Pack/Traps/Saw/2cfa1cffe1380dd56016085e018c4b68844c6f669e67925dd365481f8ef26586_Saw_On_5.png",
          "name": "Saw_On_5.png"
        }
      },
      {
        "alwaysLoaded": false,
        "file": "assets/Saw_On_6.png",
        "kind": "image",
        "metadata": "",
        "name": "Saw_On_6.png",
        "smoothed": false,
        "userAdded": false,
        "origin": {
          "identifier": "https://asset-resources.gdevelop.io/public-resources/Pixel Adventure Pack/Traps/Saw/75d8836f8bfc835f3217c0468d04f8aae970f136231c792f1251b73f5e868058_Saw_On_6.png",
          "name": "Saw_On_6.png"
        }
      },
      {
        "alwaysLoaded": false,
        "file": "assets/Saw_On_7.png",
        "kind": "image",
        "metadata": "",
        "name": "Saw_On_7.png",
        "smoothed": false,
        "userAdded": false,
        "origin": {
          "identifier": "https://asset-resources.gdevelop.io/public-resources/Pixel Adventure Pack/Traps/Saw/6351b1a83d1930df91b19b49cc23a375aa154ee74f7a31280acc6abb6f1b1fd2_Saw_On_7.png",
          "name": "Saw_On_7.png"
        }
      },
      {
        "alwaysLoaded": false,
        "file": "assets/Saw_On_8.png",
        "kind": "image",
        "metadata": "",
        "name": "Saw_On_8.png",
        "smoothed": false,
        "userAdded": false,
        "origin": {
          "identifier": "https://asset-resources.gdevelop.io/public-resources/Pixel Adventure Pack/Traps/Saw/63cce13ef5f9e917ed2de1359357510061e462e6cc8183553c0fb0c70a3c03f9_Saw_On_8.png",
          "name": "Saw_On_8.png"
        }
      },
      {
        "alwaysLoaded": false,
        "file": "assets/On.png",
        "kind": "image",
        "metadata": "{\"extension\":\".png\"}",
        "name": "On",
        "smoothed": true,
        "userAdded": false
      },
      {
        "alwaysLoaded": false,
        "file": "assets/On2.png",
        "kind": "image",
        "metadata": "{\"extension\":\".png\"}",
        "name": "On2",
        "smoothed": true,
        "userAdded": false
      },
      {
        "alwaysLoaded": false,
        "file": "assets/On3.png",
        "kind": "image",
        "metadata": "{\"extension\":\".png\"}",
        "name": "On3",
        "smoothed": true,
        "userAdded": false
      },
      {
        "alwaysLoaded": false,
        "file": "assets/On4.png",
        "kind": "image",
        "metadata": "{\"extension\":\".png\"}",
        "name": "On4",
        "smoothed": true,
        "userAdded": false
      },
      {
        "alwaysLoaded": false,
        "file": "assets/On5.png",
        "kind": "image",
        "metadata": "{\"extension\":\".png\"}",
        "name": "On5",
        "smoothed": true,
        "userAdded": false
      },
      {
        "alwaysLoaded": false,
        "file": "assets/On6.png",
        "kind": "image",
        "metadata": "{\"extension\":\".png\"}",
        "name": "On6",
        "smoothed": true,
        "userAdded": false
      },
      {
        "alwaysLoaded": false,
        "file": "assets/On7.png",
        "kind": "image",
        "metadata": "{\"extension\":\".png\"}",
        "name": "On7",
        "smoothed": true,
        "userAdded": false
      },
      {
        "alwaysLoaded": false,
        "file": "assets/On8.png",
        "kind": "image",
        "metadata": "{\"extension\":\".png\"}",
        "name": "On8",
        "smoothed": true,
        "userAdded": false
      },
      {
        "file": "assets/PressStart2P-Regular.ttf",
        "kind": "font",
        "metadata": "",
        "name": "44904f17cd5efc06565a08838d627234cda763a6406798f0cbbdf1cf60c676b3_PressStart2P-Regular.ttf",
        "userAdded": false,
        "origin": {
          "identifier": "https://asset-resources.gdevelop.io/public-resources/Open Font License/44904f17cd5efc06565a08838d627234cda763a6406798f0cbbdf1cf60c676b3_PressStart2P-Regular.ttf",
          "name": "gdevelop-asset-store"
        }
      },
      {
        "alwaysLoaded": false,
        "file": "hex-bolt-clipart-design-illustration-free-png.webp",
        "kind": "image",
        "metadata": "",
        "name": "hex-bolt-clipart-design-illustration-free-png.webp",
        "smoothed": true,
        "userAdded": false
      },
      {
        "alwaysLoaded": false,
        "file": "pngimg.com - clothes_button_PNG14157.png",
        "kind": "image",
        "metadata": "",
        "name": "pngimg.com - clothes_button_PNG14157.png",
        "smoothed": true,
        "userAdded": false
      },
      {
        "alwaysLoaded": false,
        "file": "sewing-thread-with-needle-722vOl9-600.jpg",
        "kind": "image",
        "metadata": "",
        "name": "sewing-thread-with-needle-722vOl9-600.jpg",
        "smoothed": true,
        "userAdded": false
      },
      {
        "alwaysLoaded": false,
        "file": "assets/hex-bolt-clipart-design-illustration-free-png.png",
        "kind": "image",
        "metadata": "{\"extension\":\".png\"}",
        "name": "hex-bolt-clipart-design-illustration-free-png",
        "smoothed": true,
        "userAdded": false
      },
      {
        "alwaysLoaded": false,
        "file": "assets/hex-bolt-clipart-design-illustration-free-png2.png",
        "kind": "image",
        "metadata": "{\"extension\":\".png\"}",
        "name": "hex-bolt-clipart-design-illustration-free-png2",
        "smoothed": true,
        "userAdded": false
      },
      {
        "alwaysLoaded": false,
        "file": "assets/pngimg.com - clothes_button_PNG14157.png",
        "kind": "image",
        "metadata": "{\"extension\":\".png\"}",
        "name": "pngimg.com - clothes_button_PNG14157",
        "smoothed": true,
        "userAdded": false
      },
      {
        "alwaysLoaded": false,
        "file": "assets/pngimg.com - clothes_button_PNG14158.png",
        "kind": "image",
        "metadata": "{\"extension\":\".png\"}",
        "name": "pngimg.com - clothes_button_PNG14158",
        "smoothed": true,
        "userAdded": false
      },
      {
        "alwaysLoaded": false,
        "file": "pngtree-a-spool-of-thread-png-image_11518872.png",
        "kind": "image",
        "metadata": "",
        "name": "pngtree-a-spool-of-thread-png-image_11518872.png",
        "smoothed": true,
        "userAdded": false
      },
      {
        "alwaysLoaded": false,
        "file": "assets/NewSprite4.png",
        "kind": "image",
        "metadata": "{\"extension\":\".png\",\"localFilePath\":\"assets/NewSprite4.png\"}",
        "name": "NewSprite4",
        "smoothed": true,
        "userAdded": false
      }
    ],
    "resourceFolders": []
  },
  "objects": [],
  "objectsFolderStructure": {
    "folderName": "__ROOT"
  },
  "objectsGroups": [],
  "variables": [
    {
      "name": "Time",
      "type": "number",
      "value": 0
    },
    {
      "name": "HasItem",
      "type": "boolean",
      "value": false
    },
    {
      "name": "HasBolt",
      "type": "boolean",
      "value": false
    },
    {
      "name": "HasButton",
      "type": "boolean",
      "value": false
    },
    {
      "name": "HasSpool",
      "type": "boolean",
      "value": false
    }
  ],
  "layouts": [
    {
      "b": 180,
      "disableInputWhenNotFocused": true,
      "mangledName": "Untitled_32scene",
      "name": "Untitled scene",
      "r": 184,
      "standardSortMethod": true,
      "stopSoundsOnStartup": true,
      "title": "",
      "v": 182,
      "uiSettings": {
        "grid": false,
        "gridType": "rectangular",
        "gridWidth": 32,
        "gridHeight": 32,
        "gridOffsetX": 0,
        "gridOffsetY": 0,
        "gridColor": 10401023,
        "gridAlpha": 0.8,
        "snap": false,
        "zoomFactor": 0.8141881203709929,
        "windowMask": false
      },
      "objectsGroups": [],
      "variables": [
        {
          "name": "InvFull",
          "type": "boolean",
          "value": false
        }
      ],
      "instances": [
        {
          "angle": 0,
          "customSize": true,
          "depth": 1,
          "height": 65,
          "keepRatio": true,
          "layer": "",
          "name": "Player",
          "persistentUuid": "7f486a11-1601-400d-b40e-9376e0589240",
          "width": 59,
          "x": 612,
          "y": 341,
          "zOrder": 17,
          "numberProperties": [],
          "stringProperties": [],
          "initialVariables": []
        },
        {
          "angle": 0,
          "customSize": true,
          "depth": 17,
          "height": 243,
          "keepRatio": true,
          "layer": "",
          "name": "Nuts_Bolts",
          "persistentUuid": "a01bb145-95ff-4814-832d-19e143366be1",
          "width": 98,
          "x": 64,
          "y": 245,
          "zOrder": 2,
          "numberProperties": [],
          "stringProperties": [],
          "initialVariables": []
        },
        {
          "angle": 0,
          "customSize": true,
          "depth": 1,
          "height": 96,
          "keepRatio": true,
          "layer": "",
          "name": "Button",
          "persistentUuid": "933a9a66-5902-4100-9db7-5ab19f974a34",
          "width": 285,
          "x": 510,
          "y": 76,
          "zOrder": 3,
          "numberProperties": [],
          "stringProperties": [],
          "initialVariables": []
        },
        {
          "angle": 0,
          "customSize": true,
          "depth": 1,
          "height": 246,
          "keepRatio": true,
          "layer": "",
          "name": "Cloth",
          "persistentUuid": "6b6b162e-df94-4621-9dee-e6b7d6dc9ca5",
          "width": 100,
          "x": 1079,
          "y": 234,
          "zOrder": 4,
          "numberProperties": [],
          "stringProperties": [],
          "initialVariables": []
        },
        {
          "angle": 0,
          "customSize": true,
          "depth": 1,
          "height": 12,
          "keepRatio": true,
          "layer": "",
          "name": "Saw_Track",
          "persistentUuid": "6db56bca-8731-4f0b-a272-548b529d516c",
          "width": 793,
          "x": 240,
          "y": 174,
          "zOrder": 7,
          "numberProperties": [],
          "stringProperties": [],
          "initialVariables": []
        },
        {
          "angle": 0,
          "customSize": true,
          "depth": 2,
          "height": 75,
          "keepRatio": true,
          "layer": "",
          "name": "Crafting_Table",
          "persistentUuid": "fb17ddda-0d4f-4e2f-b155-00f65daf17fb",
          "width": 76,
          "x": 792,
          "y": 504,
          "zOrder": 9,
          "numberProperties": [],
          "stringProperties": [],
          "initialVariables": []
        },
        {
          "angle": 0,
          "customSize": false,
          "height": 0,
          "keepRatio": true,
          "layer": "",
          "name": "Invisible_Saw_barrier_A",
          "persistentUuid": "a3499659-2b68-43b2-8375-41285ee6c52a",
          "width": 0,
          "x": 214,
          "y": 158,
          "zOrder": 10,
          "numberProperties": [],
          "stringProperties": [],
          "initialVariables": []
        },
        {
          "angle": 0,
          "customSize": false,
          "height": 0,
          "keepRatio": true,
          "layer": "",
          "name": "Invisible_Saw_Barrier_B",
          "persistentUuid": "fe0dc0be-f04e-4f74-86e8-4e7008402376",
          "width": 0,
          "x": 1027,
          "y": 160,
          "zOrder": 11,
          "numberProperties": [],
          "stringProperties": [],
          "initialVariables": []
        },
        {
          "angle": 0,
          "customSize": true,
          "depth": 1,
          "height": 26,
          "keepRatio": true,
          "layer": "",
          "name": "Conveyor_Belt",
          "persistentUuid": "291c663d-7bbe-4d1e-88a5-d2abdfb0ae4d",
          "width": 635,
          "x": 307,
          "y": 610,
          "zOrder": 0,
          "numberProperties": [],
          "stringProperties": [],
          "initialVariables": []
        },
        {
          "angle": 270,
          "customSize": true,
          "depth": 1,
          "height": 60,
          "keepRatio": true,
          "layer": "",
          "name": "Barrier",
          "persistentUuid": "1096b83d-1bfc-43f5-98a3-fab4683cc425",
          "width": 84,
          "x": 814,
          "y": 602,
          "zOrder": 13,
          "numberProperties": [],
          "stringProperties": [],
          "initialVariables": []
        },
        {
          "angle": 0,
          "customSize": true,
          "depth": 4,
          "height": 70,
          "keepRatio": true,
          "layer": "",
          "name": "Toy1",
          "persistentUuid": "d5f09476-f366-4710-adde-919178a4998d",
          "width": 70,
          "x": 315,
          "y": 580,
          "zOrder": 14,
          "numberProperties": [],
          "stringProperties": [],
          "initialVariables": []
        },
        {
          "angle": 0,
          "customSize": true,
          "depth": 1,
          "height": 647,
          "keepRatio": true,
          "layer": "",
          "name": "WoodBackground",
          "persistentUuid": "00ecc5af-5e4a-4723-b878-63830c1829e3",
          "width": 1249,
          "x": -3,
          "y": 74,
          "zOrder": -1,
          "numberProperties": [],
          "stringProperties": [],
          "initialVariables": []
        },
        {
          "angle": 0,
          "customSize": false,
          "height": 0,
          "keepRatio": true,
          "layer": "",
          "name": "wall_placeholder",
          "persistentUuid": "643753bb-794d-42f2-9f49-c0335bf480d0",
          "width": 0,
          "x": 579,
          "y": 29,
          "zOrder": 15,
          "numberProperties": [],
          "stringProperties": [],
          "initialVariables": []
        },
        {
          "angle": 0,
          "customSize": true,
          "depth": 1,
          "height": 80,
          "keepRatio": true,
          "layer": "",
          "name": "Saw",
          "persistentUuid": "f13a0dc4-1140-42c3-90aa-a14fb5275a0c",
          "width": 100,
          "x": 259,
          "y": 141,
          "zOrder": 16,
          "numberProperties": [],
          "stringProperties": [],
          "initialVariables": []
        },
        {
          "angle": 0,
          "customSize": false,
          "height": 0,
          "keepRatio": true,
          "layer": "UI",
          "name": "Time_Remaining",
          "persistentUuid": "f0701739-3c41-40ed-8d24-a6213f7582a4",
          "width": 0,
          "x": 10,
          "y": 18,
          "zOrder": 17,
          "numberProperties": [],
          "stringProperties": [],
          "initialVariables": []
        },
        {
          "angle": 0,
          "customSize": false,
          "height": 0,
          "keepRatio": true,
          "layer": "UI",
          "name": "TimeNum",
          "persistentUuid": "14621505-8341-4abc-b95a-8918c2c1e5fe",
          "width": 0,
          "x": 309,
          "y": 17,
          "zOrder": 18,
          "numberProperties": [],
          "stringProperties": [],
          "initialVariables": []
        }
      ],
      "objects": [
        {
          "adaptCollisionMaskAutomatically": true,
          "assetStoreId": "",
          "name": "Player",
          "type": "Sprite",
          "updateIfNotVisible": false,
          "variables": [],
          "effects": [],
          "behaviors": [
            {
              "name": "TopDownMovement",
              "type": "TopDownMovementBehavior::TopDownMovementBehavior",
              "acceleration": 900000,
              "deceleration": 900000,
              "maxSpeed": 275,
              "allowDiagonals": true,
              "angleOffset": 0,
              "angularMaxSpeed": 0,
              "customIsometryAngle": 30,
              "ignoreDefaultControls": false,
              "movementAngleOffset": 0,
              "rotateObject": false,
              "viewpoint": "TopDown"
            }
          ],
          "animations": [
            {
              "name": "",
              "useMultipleDirections": false,
              "directions": [
                {
                  "looping": false,
                  "timeBetweenFrames": 0.08,
                  "sprites": [
                    {
                      "hasCustomCollisionMask": true,
                      "image": "TUFF.png",
                      "points": [],
                      "originPoint": {
                        "name": "origine",
                        "x": 0,
                        "y": 0
                      },
                      "centerPoint": {
                        "automatic": true,
                        "name": "centre",
                        "x": 0,
                        "y": 0
                      },
                      "customCollisionMask": [
                        [
                          {
                            "x": 0,
                            "y": 0
                          },
                          {
                            "x": 234,
                            "y": 0
                          },
                          {
                            "x": 234,
                            "y": 258
                          },
                          {
                            "x": 0,
                            "y": 258
                          }
                        ]
                      ]
                    }
                  ]
                }
              ]
            }
          ]
        },
        {
          "assetStoreId": "",
          "height": 32,
          "name": "Nuts_Bolts",
          "texture": "images.jpg",
          "type": "TiledSpriteObject::TiledSprite",
          "width": 32,
          "variables": [],
          "effects": [],
          "behaviors": []
        },
        {
          "assetStoreId": "",
          "height": 64,
          "name": "Button",
          "texture": "81U7rrsM8zL.jpg",
          "type": "TiledSpriteObject::TiledSprite",
          "width": 64,
          "variables": [],
          "effects": [],
          "behaviors": []
        },
        {
          "assetStoreId": "",
          "height": 32,
          "name": "Cloth",
          "texture": "8-x-8-Microfiber-Silk-Lens-Cloth-Blue_1200x600_crop_center.webp",
          "type": "TiledSpriteObject::TiledSprite",
          "width": 32,
          "variables": [],
          "effects": [],
          "behaviors": []
        },
        {
          "adaptCollisionMaskAutomatically": true,
          "assetStoreId": "",
          "name": "Saw_Track",
          "type": "Sprite",
          "updateIfNotVisible": false,
          "variables": [],
          "effects": [],
          "behaviors": [],
          "animations": [
            {
              "name": "NewSprite2",
              "useMultipleDirections": false,
              "directions": [
                {
                  "looping": false,
                  "metadata": "{\"pskl\":{}}",
                  "timeBetweenFrames": 0.08,
                  "sprites": [
                    {
                      "hasCustomCollisionMask": true,
                      "image": "NewSprite2",
                      "points": [],
                      "originPoint": {
                        "name": "origine",
                        "x": 0,
                        "y": 0
                      },
                      "centerPoint": {
                        "automatic": true,
                        "name": "centre",
                        "x": 0,
                        "y": 0
                      },
                      "customCollisionMask": [
                        [
                          {
                            "x": 0,
                            "y": 0
                          },
                          {
                            "x": 64,
                            "y": 0
                          },
                          {
                            "x": 64,
                            "y": 64
                          },
                          {
                            "x": 0,
                            "y": 64
                          }
                        ]
                      ]
                    }
                  ]
                }
              ]
            }
          ]
        },
        {
          "adaptCollisionMaskAutomatically": true,
          "assetStoreId": "",
          "name": "Crafting_Table",
          "type": "Sprite",
          "updateIfNotVisible": false,
          "variables": [],
          "effects": [],
          "behaviors": [],
          "animations": [
            {
              "name": "",
              "useMultipleDirections": false,
              "directions": [
                {
                  "looping": false,
                  "timeBetweenFrames": 0.08,
                  "sprites": [
                    {
                      "hasCustomCollisionMask": true,
                      "image": "Crafting_Table_JE4_BE3.webp",
                      "points": [],
                      "originPoint": {
                        "name": "origine",
                        "x": 0,
                        "y": 0
                      },
                      "centerPoint": {
                        "automatic": true,
                        "name": "centre",
                        "x": 0,
                        "y": 0
                      },
                      "customCollisionMask": [
                        [
                          {
                            "x": 16,
                            "y": 2
                          },
                          {
                            "x": 284,
                            "y": 2
                          },
                          {
                            "x": 284,
                            "y": 298
                          },
                          {
                            "x": 16,
                            "y": 298
                          }
                        ]
                      ]
                    }
                  ]
                }
              ]
            }
          ]
        },
        {
          "adaptCollisionMaskAutomatically": true,
          "assetStoreId": "",
          "name": "Invisible_Saw_barrier_A",
          "type": "Sprite",
          "updateIfNotVisible": false,
          "variables": [],
          "effects": [],
          "behaviors": [],
          "animations": [
            {
              "name": "Invisible_Saw_barrier_A",
              "useMultipleDirections": false,
              "directions": [
                {
                  "looping": false,
                  "metadata": "{\"pskl\":{}}",
                  "timeBetweenFrames": 0.08,
                  "sprites": [
                    {
                      "hasCustomCollisionMask": true,
                      "image": "Invisible_Saw_barrier_A",
                      "points": [],
                      "originPoint": {
                        "name": "origine",
                        "x": 0,
                        "y": 0
                      },
                      "centerPoint": {
                        "automatic": true,
                        "name": "centre",
                        "x": 0,
                        "y": 0
                      },
                      "customCollisionMask": [
                        [
                          {
                            "x": 0,
                            "y": 0
                          },
                          {
                            "x": 64,
                            "y": 0
                          },
                          {
                            "x": 64,
                            "y": 64
                          },
                          {
                            "x": 0,
                            "y": 64
                          }
                        ]
                      ]
                    }
                  ]
                }
              ]
            }
          ]
        },
        {
          "adaptCollisionMaskAutomatically": true,
          "assetStoreId": "",
          "name": "Invisible_Saw_Barrier_B",
          "type": "Sprite",
          "updateIfNotVisible": false,
          "variables": [],
          "effects": [],
          "behaviors": [],
          "animations": [
            {
              "name": "Invisible_Saw_Barrier_B",
              "useMultipleDirections": false,
              "directions": [
                {
                  "looping": false,
                  "metadata": "{\"pskl\":{}}",
                  "timeBetweenFrames": 0.08,
                  "sprites": [
                    {
                      "hasCustomCollisionMask": true,
                      "image": "Invisible_Saw_Barrier_B",
                      "points": [],
                      "originPoint": {
                        "name": "origine",
                        "x": 0,
                        "y": 0
                      },
                      "centerPoint": {
                        "automatic": true,
                        "name": "centre",
                        "x": 0,
                        "y": 0
                      },
                      "customCollisionMask": [
                        [
                          {
                            "x": 0,
                            "y": 0
                          },
                          {
                            "x": 64,
                            "y": 0
                          },
                          {
                            "x": 64,
                            "y": 64
                          },
                          {
                            "x": 0,
                            "y": 64
                          }
                        ]
                      ]
                    }
                  ]
                }
              ]
            }
          ]
        },
        {
          "assetStoreId": "",
          "height": 32,
          "name": "Conveyor_Belt",
          "texture": "NewTiledSprite",
          "type": "TiledSpriteObject::TiledSprite",
          "width": 32,
          "variables": [],
          "effects": [],
          "behaviors": []
        },
        {
          "adaptCollisionMaskAutomatically": false,
          "assetStoreId": "",
          "name": "Barrier",
          "type": "Sprite",
          "updateIfNotVisible": false,
          "variables": [],
          "effects": [],
          "behaviors": [],
          "animations": [
            {
              "name": "NewSprite",
              "useMultipleDirections": false,
              "directions": [
                {
                  "looping": false,
                  "metadata": "{\"pskl\":{}}",
                  "timeBetweenFrames": 0.08,
                  "sprites": [
                    {
                      "hasCustomCollisionMask": true,
                      "image": "NewSprite3",
                      "points": [],
                      "originPoint": {
                        "name": "origine",
                        "x": 0,
                        "y": 0
                      },
                      "centerPoint": {
                        "automatic": true,
                        "name": "centre",
                        "x": 0,
                        "y": 0
                      },
                      "customCollisionMask": [
                        [
                          {
                            "x": 25,
                            "y": 8
                          },
                          {
                            "x": 61,
                            "y": 8
                          },
                          {
                            "x": 61,
                            "y": 19
                          },
                          {
                            "x": 25,
                            "y": 19
                          }
                        ]
                      ]
                    }
                  ]
                }
              ]
            }
          ]
        },
        {
          "adaptCollisionMaskAutomatically": true,
          "assetStoreId": "c326b49fa400bfc5f51a7c8d69d9d2b228370e9244ab621f919f9a5f0943659d",
          "name": "Toy1",
          "type": "Sprite",
          "updateIfNotVisible": false,
          "variables": [],
          "effects": [],
          "behaviors": [],
          "animations": [
            {
              "name": "Spinning",
              "useMultipleDirections": false,
              "directions": [
                {
                  "looping": false,
                  "timeBetweenFrames": 9999,
                  "sprites": [
                    {
                      "hasCustomCollisionMask": true,
                      "image": "Bun_Spinning_1.png",
                      "points": [],
                      "originPoint": {
                        "name": "origine",
                        "x": 0,
                        "y": 0
                      },
                      "centerPoint": {
                        "automatic": true,
                        "name": "centre",
                        "x": 0,
                        "y": 0
                      },
                      "customCollisionMask": [
                        [
                          {
                            "x": 3,
                            "y": 0
                          },
                          {
                            "x": 13,
                            "y": 0
                          },
                          {
                            "x": 13,
                            "y": 16
                          },
                          {
                            "x": 3,
                            "y": 16
                          }
                        ]
                      ]
                    }
                  ]
                }
              ]
            }
          ]
        },
        {
          "assetStoreId": "08d9802965c3beec17416c0e0ff3f459710d2e2bf155c0e0ece4459d4efa98ec",
          "bottomMargin": 64,
          "height": 192,
          "leftMargin": 64,
          "name": "WoodBackground",
          "rightMargin": 64,
          "texture": "9patch_Wood Background_all_64.png",
          "tiled": true,
          "topMargin": 64,
          "type": "PanelSpriteObject::PanelSprite",
          "width": 192,
          "variables": [],
          "effects": [],
          "behaviors": []
        },
        {
          "assetStoreId": "",
          "bold": false,
          "italic": false,
          "name": "wall_placeholder",
          "smoothed": true,
          "type": "TextObject::Text",
          "underlined": false,
          "variables": [],
          "effects": [],
          "behaviors": [],
          "string": "WALL GOES HERE",
          "font": "",
          "textAlignment": "left",
          "characterSize": 20,
          "color": {
            "b": 0,
            "g": 0,
            "r": 0
          },
          "content": {
            "bold": false,
            "isOutlineEnabled": false,
            "isShadowEnabled": false,
            "italic": false,
            "outlineColor": "255;255;255",
            "outlineThickness": 2,
            "shadowAngle": 90,
            "shadowBlurRadius": 2,
            "shadowColor": "0;0;0",
            "shadowDistance": 4,
            "shadowOpacity": 127,
            "smoothed": true,
            "underlined": false,
            "text": "WALL GOES HERE",
            "font": "",
            "textAlignment": "left",
            "verticalTextAlignment": "top",
            "characterSize": 20,
            "color": "0;0;0"
          }
        },
        {
          "adaptCollisionMaskAutomatically": false,
          "assetStoreId": "04458b0edc6d387709a7393d302010db9933d6d8fcd0e8150c6db22cdea18d2b",
          "name": "Saw",
          "type": "Sprite",
          "updateIfNotVisible": false,
          "variables": [],
          "effects": [],
          "behaviors": [],
          "animations": [
            {
              "name": "On",
              "useMultipleDirections": false,
              "directions": [
                {
                  "looping": true,
                  "metadata": "{\"pskl\":{}}",
                  "timeBetweenFrames": 0.125,
                  "sprites": [
                    {
                      "hasCustomCollisionMask": true,
                      "image": "On",
                      "points": [],
                      "originPoint": {
                        "name": "origine",
                        "x": 0,
                        "y": 0
                      },
                      "centerPoint": {
                        "automatic": true,
                        "name": "centre",
                        "x": 0,
                        "y": 0
                      },
                      "customCollisionMask": [
                        [
                          {
                            "x": 5,
                            "y": 5.5
                          },
                          {
                            "x": 32,
                            "y": 5.5
                          },
                          {
                            "x": 32,
                            "y": 19
                          },
                          {
                            "x": 5,
                            "y": 19
                          }
                        ]
                      ]
                    },
                    {
                      "hasCustomCollisionMask": true,
                      "image": "On2",
                      "points": [],
                      "originPoint": {
                        "name": "origine",
                        "x": 0,
                        "y": 0
                      },
                      "centerPoint": {
                        "automatic": true,
                        "name": "centre",
                        "x": 0,
                        "y": 0
                      },
                      "customCollisionMask": [
                        [
                          {
                            "x": 5,
                            "y": 5.5
                          },
                          {
                            "x": 32,
                            "y": 5.5
                          },
                          {
                            "x": 32,
                            "y": 19
                          },
                          {
                            "x": 5,
                            "y": 19
                          }
                        ]
                      ]
                    },
                    {
                      "hasCustomCollisionMask": true,
                      "image": "On3",
                      "points": [],
                      "originPoint": {
                        "name": "origine",
                        "x": 0,
                        "y": 0
                      },
                      "centerPoint": {
                        "automatic": true,
                        "name": "centre",
                        "x": 0,
                        "y": 0
                      },
                      "customCollisionMask": [
                        [
                          {
                            "x": 5,
                            "y": 5.5
                          },
                          {
                            "x": 32,
                            "y": 5.5
                          },
                          {
                            "x": 32,
                            "y": 19
                          },
                          {
                            "x": 5,
                            "y": 19
                          }
                        ]
                      ]
                    },
                    {
                      "hasCustomCollisionMask": true,
                      "image": "On4",
                      "points": [],
                      "originPoint": {
                        "name": "origine",
                        "x": 0,
                        "y": 0
                      },
                      "centerPoint": {
                        "automatic": true,
                        "name": "centre",
                        "x": 0,
                        "y": 0
                      },
                      "customCollisionMask": [
                        [
                          {
                            "x": 5,
                            "y": 5.5
                          },
                          {
                            "x": 32,
                            "y": 5.5
                          },
                          {
                            "x": 32,
                            "y": 19
                          },
                          {
                            "x": 5,
                            "y": 19
                          }
                        ]
                      ]
                    },
                    {
                      "hasCustomCollisionMask": true,
                      "image": "On5",
                      "points": [],
                      "originPoint": {
                        "name": "origine",
                        "x": 0,
                        "y": 0
                      },
                      "centerPoint": {
                        "automatic": true,
                        "name": "centre",
                        "x": 0,
                        "y": 0
                      },
                      "customCollisionMask": [
                        [
                          {
                            "x": 5,
                            "y": 5.5
                          },
                          {
                            "x": 32,
                            "y": 5.5
                          },
                          {
                            "x": 32,
                            "y": 19
                          },
                          {
                            "x": 5,
                            "y": 19
                          }
                        ]
                      ]
                    },
                    {
                      "hasCustomCollisionMask": true,
                      "image": "On6",
                      "points": [],
                      "originPoint": {
                        "name": "origine",
                        "x": 0,
                        "y": 0
                      },
                      "centerPoint": {
                        "automatic": true,
                        "name": "centre",
                        "x": 0,
                        "y": 0
                      },
                      "customCollisionMask": [
                        [
                          {
                            "x": 5,
                            "y": 5.5
                          },
                          {
                            "x": 32,
                            "y": 5.5
                          },
                          {
                            "x": 32,
                            "y": 19
                          },
                          {
                            "x": 5,
                            "y": 19
                          }
                        ]
                      ]
                    },
                    {
                      "hasCustomCollisionMask": true,
                      "image": "On7",
                      "points": [],
                      "originPoint": {
                        "name": "origine",
                        "x": 0,
                        "y": 0
                      },
                      "centerPoint": {
                        "automatic": true,
                        "name": "centre",
                        "x": 0,
                        "y": 0
                      },
                      "customCollisionMask": [
                        [
                          {
                            "x": 5,
                            "y": 5.5
                          },
                          {
                            "x": 32,
                            "y": 5.5
                          },
                          {
                            "x": 32,
                            "y": 19
                          },
                          {
                            "x": 5,
                            "y": 19
                          }
                        ]
                      ]
                    },
                    {
                      "hasCustomCollisionMask": true,
                      "image": "On8",
                      "points": [],
                      "originPoint": {
                        "name": "origine",
                        "x": 0,
                        "y": 0
                      },
                      "centerPoint": {
                        "automatic": true,
                        "name": "centre",
                        "x": 0,
                        "y": 0
                      },
                      "customCollisionMask": [
                        [
                          {
                            "x": 5,
                            "y": 5.5
                          },
                          {
                            "x": 32,
                            "y": 5.5
                          },
                          {
                            "x": 32,
                            "y": 19
                          },
                          {
                            "x": 5,
                            "y": 19
                          }
                        ]
                      ]
                    }
                  ]
                }
              ]
            },
            {
              "name": "Off",
              "useMultipleDirections": false,
              "directions": [
                {
                  "looping": true,
                  "timeBetweenFrames": 0.025,
                  "sprites": [
                    {
                      "hasCustomCollisionMask": true,
                      "image": "Saw_Off.png",
                      "points": [],
                      "originPoint": {
                        "name": "origine",
                        "x": 0,
                        "y": 0
                      },
                      "centerPoint": {
                        "automatic": true,
                        "name": "centre",
                        "x": 0,
                        "y": 0
                      },
                      "customCollisionMask": [
                        [
                          {
                            "x": 5,
                            "y": 5.5
                          },
                          {
                            "x": 32,
                            "y": 5.5
                          },
                          {
                            "x": 32,
                            "y": 19
                          },
                          {
                            "x": 5,
                            "y": 19
                          }
                        ]
                      ]
                    }
                  ]
                }
              ]
            }
          ]
        },
        {
          "assetStoreId": "",
          "bold": false,
          "italic": false,
          "name": "Time_Remaining",
          "smoothed": true,
          "type": "TextObject::Text",
          "underlined": false,
          "variables": [],
          "effects": [],
          "behaviors": [],
          "string": "Time Remaining:",
          "font": "44904f17cd5efc06565a08838d627234cda763a6406798f0cbbdf1cf60c676b3_PressStart2P-Regular.ttf",
          "textAlignment": "left",
          "characterSize": 20,
          "color": {
            "b": 0,
            "g": 0,
            "r": 0
          },
          "content": {
            "bold": false,
            "isOutlineEnabled": false,
            "isShadowEnabled": false,
            "italic": false,
            "outlineColor": "255;255;255",
            "outlineThickness": 2,
            "shadowAngle": 90,
            "shadowBlurRadius": 2,
            "shadowColor": "0;0;0",
            "shadowDistance": 4,
            "shadowOpacity": 127,
            "smoothed": true,
            "underlined": false,
            "text": "Time Remaining:",
            "font": "44904f17cd5efc06565a08838d627234cda763a6406798f0cbbdf1cf60c676b3_PressStart2P-Regular.ttf",
            "textAlignment": "left",
            "verticalTextAlignment": "top",
            "characterSize": 20,
            "color": "0;0;0"
          }
        },
        {
          "assetStoreId": "",
          "bold": false,
          "italic": false,
          "name": "TimeNum",
          "smoothed": true,
          "type": "TextObject::Text",
          "underlined": false,
          "variables": [],
          "effects": [],
          "behaviors": [],
          "string": "120",
          "font": "44904f17cd5efc06565a08838d627234cda763a6406798f0cbbdf1cf60c676b3_PressStart2P-Regular.ttf",
          "textAlignment": "left",
          "characterSize": 20,
          "color": {
            "b": 0,
            "g": 0,
            "r": 0
          },
          "content": {
            "bold": false,
            "isOutlineEnabled": false,
            "isShadowEnabled": false,
            "italic": false,
            "outlineColor": "255;255;255",
            "outlineThickness": 2,
            "shadowAngle": 90,
            "shadowBlurRadius": 2,
            "shadowColor": "0;0;0",
            "shadowDistance": 4,
            "shadowOpacity": 127,
            "smoothed": true,
            "underlined": false,
            "text": "120",
            "font": "44904f17cd5efc06565a08838d627234cda763a6406798f0cbbdf1cf60c676b3_PressStart2P-Regular.ttf",
            "textAlignment": "left",
            "verticalTextAlignment": "top",
            "characterSize": 20,
            "color": "0;0;0"
          }
        },
        {
          "adaptCollisionMaskAutomatically": true,
          "assetStoreId": "",
          "name": "Bolt",
          "type": "Sprite",
          "updateIfNotVisible": false,
          "variables": [],
          "effects": [],
          "behaviors": [],
          "animations": [
            {
              "name": "hex-bolt-clipart-design-illustration-free-png",
              "useMultipleDirections": false,
              "directions": [
                {
                  "looping": false,
                  "metadata": "{\"pskl\":{}}",
                  "timeBetweenFrames": 0.08,
                  "sprites": [
                    {
                      "hasCustomCollisionMask": true,
                      "image": "hex-bolt-clipart-design-illustration-free-png2",
                      "points": [],
                      "originPoint": {
                        "name": "origine",
                        "x": 0,
                        "y": 0
                      },
                      "centerPoint": {
                        "automatic": true,
                        "name": "centre",
                        "x": 0,
                        "y": 0
                      },
                      "customCollisionMask": [
                        [
                          {
                            "x": 0,
                            "y": 0
                          },
                          {
                            "x": 32,
                            "y": 0
                          },
                          {
                            "x": 32,
                            "y": 32
                          },
                          {
                            "x": 0,
                            "y": 32
                          }
                        ]
                      ]
                    }
                  ]
                }
              ]
            }
          ]
        },
        {
          "adaptCollisionMaskAutomatically": true,
          "assetStoreId": "",
          "name": "Button2",
          "type": "Sprite",
          "updateIfNotVisible": false,
          "variables": [],
          "effects": [],
          "behaviors": [],
          "animations": [
            {
              "name": "pngimg.com - clothes_button_PNG14157",
              "useMultipleDirections": false,
              "directions": [
                {
                  "looping": false,
                  "metadata": "{\"pskl\":{}}",
                  "timeBetweenFrames": 0.08,
                  "sprites": [
                    {
                      "hasCustomCollisionMask": true,
                      "image": "pngimg.com - clothes_button_PNG14158",
                      "points": [],
                      "originPoint": {
                        "name": "origine",
                        "x": 0,
                        "y": 0
                      },
                      "centerPoint": {
                        "automatic": true,
                        "name": "centre",
                        "x": 0,
                        "y": 0
                      },
                      "customCollisionMask": [
                        [
                          {
                            "x": 0,
                            "y": 0
                          },
                          {
                            "x": 20,
                            "y": 0
                          },
                          {
                            "x": 20,
                            "y": 20
                          },
                          {
                            "x": 0,
                            "y": 20
                          }
                        ]
                      ]
                    }
                  ]
                }
              ]
            }
          ]
        },
        {
          "adaptCollisionMaskAutomatically": true,
          "assetStoreId": "",
          "name": "Spool",
          "type": "Sprite",
          "updateIfNotVisible": false,
          "variables": [],
          "effects": [],
          "behaviors": [],
          "animations": [
            {
              "name": "NewSprite",
              "useMultipleDirections": false,
              "directions": [
                {
                  "looping": false,
                  "metadata": "{\"pskl\":{}}",
                  "timeBetweenFrames": 0.08,
                  "sprites": [
                    {
                      "hasCustomCollisionMask": true,
                      "image": "NewSprite4",
                      "points": [],
                      "originPoint": {
                        "name": "origine",
                        "x": 0,
                        "y": 0
                      },
                      "centerPoint": {
                        "automatic": true,
                        "name": "centre",
                        "x": 0,
                        "y": 0
                      },
                      "customCollisionMask": [
                        [
                          {
                            "x": 13,
                            "y": 11
                          },
                          {
                            "x": 50,
                            "y": 11
                          },
                          {
                            "x": 50,
                            "y": 53
                          },
                          {
                            "x": 13,
                            "y": 53
                          }
                        ]
                      ]
                    }
                  ]
                }
              ]
            }
          ]
        }
      ],
      "objectsFolderStructure": {
        "folderName": "__ROOT",
        "children": [
          {
            "folderName": "Items",
            "children": [
              {
                "objectName": "Bolt"
              },
              {
                "objectName": "Button2"
              },
              {
                "objectName": "Spool"
              }
            ]
          },
          {
            "folderName": "UI",
            "children": [
              {
                "objectName": "Time_Remaining"
              },
              {
                "objectName": "TimeNum"
              }
            ]
          },
          {
            "folderName": "SceneAssets",
            "children": [
              {
                "objectName": "Saw"
              },
              {
                "objectName": "Player"
              },
              {
                "objectName": "Nuts_Bolts"
              },
              {
                "objectName": "Button"
              },
              {
                "objectName": "Cloth"
              },
              {
                "objectName": "Saw_Track"
              },
              {
                "objectName": "Invisible_Saw_barrier_A"
              },
              {
                "objectName": "Invisible_Saw_Barrier_B"
              },
              {
                "objectName": "Crafting_Table"
              },
              {
                "objectName": "Toy1"
              },
              {
                "objectName": "Conveyor_Belt"
              },
              {
                "objectName": "Barrier"
              }
            ]
          },
          {
            "folderName": "Background",
            "children": [
              {
                "objectName": "wall_placeholder"
              },
              {
                "objectName": "WoodBackground"
              }
            ]
          }
        ]
      },
      "events": [
        {
          "type": "BuiltinCommonInstructions::Standard",
          "conditions": [
            {
              "type": {
                "value": "CollisionNP"
              },
              "parameters": [
                "Saw",
                "Invisible_Saw_barrier_A",
                "",
                "",
                ""
              ]
            }
          ],
          "actions": [
            {
              "type": {
                "value": "Arreter"
              },
              "parameters": [
                "Saw"
              ]
            },
            {
              "type": {
                "value": "AddForceVers"
              },
              "parameters": [
                "Saw",
                "Invisible_Saw_Barrier_B",
                "225",
                "1"
              ]
            }
          ]
        },
        {
          "type": "BuiltinCommonInstructions::Standard",
          "conditions": [
            {
              "type": {
                "value": "CollisionNP"
              },
              "parameters": [
                "Saw",
                "Invisible_Saw_Barrier_B",
                "",
                "",
                ""
              ]
            }
          ],
          "actions": [
            {
              "type": {
                "value": "Arreter"
              },
              "parameters": [
                "Saw"
              ]
            },
            {
              "type": {
                "value": "AddForceVers"
              },
              "parameters": [
                "Saw",
                "Invisible_Saw_barrier_A",
                "225",
                "1"
              ]
            }
          ]
        },
        {
          "type": "BuiltinCommonInstructions::Standard",
          "conditions": [
            {
              "type": {
                "value": "CollisionNP"
              },
              "parameters": [
                "Toy1",
                "Conveyor_Belt",
                "",
                "",
                ""
              ]
            }
          ],
          "actions": [
            {
              "type": {
                "value": "AddForceVers"
              },
              "parameters": [
                "Toy1",
                "Barrier",
                ".09",
                "1"
              ]
            }
          ]
        },
        {
          "type": "BuiltinCommonInstructions::Standard",
          "conditions": [
            {
              "type": {
                "value": "CollisionNP"
              },
              "parameters": [
                "Toy1",
                "Barrier",
                "",
                "",
                ""
              ]
            }
          ],
          "actions": [
            {
              "type": {
                "value": "Arreter"
              },
              "parameters": [
                "Toy1"
              ]
            }
          ]
        },
        {
          "colorB": 228,
          "colorG": 176,
          "colorR": 74,
          "creationTime": 0,
          "name": "Timer",
          "source": "",
          "type": "BuiltinCommonInstructions::Group",
          "events": [
            {
              "type": "BuiltinCommonInstructions::Standard",
              "conditions": [
                {
                  "type": {
                    "value": "DepartScene"
                  },
                  "parameters": [
                    ""
                  ]
                }
              ],
              "actions": [
                {
                  "type": {
                    "value": "ResetTimer"
                  },
                  "parameters": [
                    "",
                    "\"SceneTime\""
                  ]
                }
              ]
            },
            {
              "type": "BuiltinCommonInstructions::Standard",
              "conditions": [],
              "actions": [
                {
                  "type": {
                    "value": "TextContainerCapability::TextContainerBehavior::SetValue"
                  },
                  "parameters": [
                    "TimeNum",
                    "Text",
                    "=",
                    "ToString(round(abs((TimerElapsedTime(\"SceneTime\")-120))))"
                  ]
                }
              ]
            },
            {
              "type": "BuiltinCommonInstructions::Standard",
              "conditions": [
                {
                  "type": {
                    "value": "CompareTimer"
                  },
                  "parameters": [
                    "",
                    "\"SceneTime\"",
                    ">=",
                    "120"
                  ]
                }
              ],
              "actions": [
                {
                  "type": {
                    "value": "TextContainerCapability::TextContainerBehavior::SetValue"
                  },
                  "parameters": [
                    "TimeNum",
                    "Text",
                    "=",
                    "\"Time's up!\""
                  ]
                }
              ]
            }
          ],
          "parameters": []
        },
        {
          "colorB": 228,
          "colorG": 176,
          "colorR": 74,
          "creationTime": 0,
          "name": "Picking up items",
          "source": "",
          "type": "BuiltinCommonInstructions::Group",
          "events": [
            {
              "type": "BuiltinCommonInstructions::Comment",
              "color": {
                "b": 109,
                "g": 230,
                "r": 255,
                "textB": 0,
                "textG": 0,
                "textR": 0
              },
              "comment": "Bolt"
            },
            {
              "type": "BuiltinCommonInstructions::Standard",
              "conditions": [
                {
                  "type": {
                    "value": "CollisionNP"
                  },
                  "parameters": [
                    "Player",
                    "Nuts_Bolts",
                    "",
                    "",
                    ""
                  ]
                },
                {
                  "type": {
                    "value": "BooleanVariable"
                  },
                  "parameters": [
                    "InvFull",
                    "=",
                    ""
                  ]
                },
                {
                  "type": {
                    "value": "BooleanVariable"
                  },
                  "parameters": [
                    "HasBolt",
                    "=",
                    ""
                  ]
                },
                {
                  "type": {
                    "value": "BuiltinCommonInstructions::Once"
                  },
                  "parameters": []
                }
              ],
              "actions": [
                {
                  "type": {
                    "value": "Create"
                  },
                  "parameters": [
                    "",
                    "Bolt",
                    "Player.X()",
                    "Player.Y()",
                    ""
                  ]
                }
              ]
            },
            {
              "type": "BuiltinCommonInstructions::Standard",
              "conditions": [
                {
                  "type": {
                    "value": "CollisionNP"
                  },
                  "parameters": [
                    "Player",
                    "Bolt",
                    "",
                    "",
                    ""
                  ]
                }
              ],
              "actions": [
                {
                  "type": {
                    "value": "MettreAutour"
                  },
                  "parameters": [
                    "Bolt",
                    "Player",
                    "32",
                    "45"
                  ]
                },
                {
                  "type": {
                    "value": "SetBooleanVariable"
                  },
                  "parameters": [
                    "InvFull",
                    "True",
                    ""
                  ]
                }
              ],
              "events": [
                {
                  "type": "BuiltinCommonInstructions::Standard",
                  "conditions": [
                    {
                      "type": {
                        "value": "BooleanVariable"
                      },
                      "parameters": [
                        "InvFull",
                        "True",
                        ""
                      ]
                    },
                    {
                      "type": {
                        "value": "BuiltinCommonInstructions::Once"
                      },
                      "parameters": []
                    }
                  ],
                  "actions": [
                    {
                      "type": {
                        "value": "SetBooleanVariable"
                      },
                      "parameters": [
                        "HasBolt",
                        "True",
                        ""
                      ]
                    }
                  ]
                }
              ]
            },
            {
              "type": "BuiltinCommonInstructions::Comment",
              "color": {
                "b": 109,
                "g": 230,
                "r": 255,
                "textB": 0,
                "textG": 0,
                "textR": 0
              },
              "comment": "Button"
            },
            {
              "type": "BuiltinCommonInstructions::Standard",
              "conditions": [
                {
                  "type": {
                    "value": "CollisionNP"
                  },
                  "parameters": [
                    "Player",
                    "Button",
                    "",
                    "",
                    ""
                  ]
                },
                {
                  "type": {
                    "value": "BooleanVariable"
                  },
                  "parameters": [
                    "InvFull",
                    "=",
                    ""
                  ]
                },
                {
                  "type": {
                    "value": "BooleanVariable"
                  },
                  "parameters": [
                    "HasButton",
                    "=",
                    ""
                  ]
                },
                {
                  "type": {
                    "value": "BuiltinCommonInstructions::Once"
                  },
                  "parameters": []
                }
              ],
              "actions": [
                {
                  "type": {
                    "value": "Create"
                  },
                  "parameters": [
                    "",
                    "Button2",
                    "Player.X()",
                    "Player.Y()",
                    ""
                  ]
                }
              ]
            },
            {
              "type": "BuiltinCommonInstructions::Standard",
              "conditions": [
                {
                  "type": {
                    "value": "CollisionNP"
                  },
                  "parameters": [
                    "Player",
                    "Button2",
                    "",
                    "",
                    ""
                  ]
                }
              ],
              "actions": [
                {
                  "type": {
                    "value": "MettreAutour"
                  },
                  "parameters": [
                    "Button2",
                    "Player",
                    "32",
                    "45"
                  ]
                },
                {
                  "type": {
                    "value": "SetBooleanVariable"
                  },
                  "parameters": [
                    "InvFull",
                    "True",
                    ""
                  ]
                }
              ],
              "events": [
                {
                  "type": "BuiltinCommonInstructions::Standard",
                  "conditions": [
                    {
                      "type": {
                        "value": "BooleanVariable"
                      },
                      "parameters": [
                        "InvFull",
                        "True",
                        ""
                      ]
                    },
                    {
                      "type": {
                        "value": "BuiltinCommonInstructions::Once"
                      },
                      "parameters": []
                    }
                  ],
                  "actions": [
                    {
                      "type": {
                        "value": "SetBooleanVariable"
                      },
                      "parameters": [
                        "HasButton",
                        "True",
                        ""
                      ]
                    }
                  ]
                }
              ]
            },
            {
              "type": "BuiltinCommonInstructions::Comment",
              "color": {
                "b": 109,
                "g": 230,
                "r": 255,
                "textB": 0,
                "textG": 0,
                "textR": 0
              },
              "comment": "Spool"
            },
            {
              "type": "BuiltinCommonInstructions::Standard",
              "conditions": [
                {
                  "type": {
                    "value": "CollisionNP"
                  },
                  "parameters": [
                    "Player",
                    "Cloth",
                    "",
                    "",
                    ""
                  ]
                },
                {
                  "type": {
                    "value": "BooleanVariable"
                  },
                  "parameters": [
                    "InvFull",
                    "=",
                    ""
                  ]
                },
                {
                  "type": {
                    "value": "BooleanVariable"
                  },
                  "parameters": [
                    "HasSpool",
                    "=",
                    ""
                  ]
                },
                {
                  "type": {
                    "value": "BuiltinCommonInstructions::Once"
                  },
                  "parameters": []
                }
              ],
              "actions": [
                {
                  "type": {
                    "value": "Create"
                  },
                  "parameters": [
                    "",
                    "Spool",
                    "Player.X()",
                    "Player.Y()",
                    ""
                  ]
                }
              ]
            },
            {
              "type": "BuiltinCommonInstructions::Standard",
              "conditions": [
                {
                  "type": {
                    "value": "CollisionNP"
                  },
                  "parameters": [
                    "Player",
                    "Spool",
                    "",
                    "",
                    ""
                  ]
                }
              ],
              "actions": [
                {
                  "type": {
                    "value": "MettreAutour"
                  },
                  "parameters": [
                    "Spool",
                    "Player",
                    "32",
                    "45"
                  ]
                },
                {
                  "type": {
                    "value": "SetBooleanVariable"
                  },
                  "parameters": [
                    "InvFull",
                    "True",
                    ""
                  ]
                }
              ],
              "events": [
                {
                  "type": "BuiltinCommonInstructions::Standard",
                  "conditions": [
                    {
                      "type": {
                        "value": "BooleanVariable"
                      },
                      "parameters": [
                        "InvFull",
                        "True",
                        ""
                      ]
                    },
                    {
                      "type": {
                        "value": "BuiltinCommonInstructions::Once"
                      },
                      "parameters": []
                    }
                  ],
                  "actions": [
                    {
                      "type": {
                        "value": "SetBooleanVariable"
                      },
                      "parameters": [
                        "HasSpool",
                        "True",
                        ""
                      ]
                    }
                  ]
                }
              ]
            }
          ],
          "parameters": []
        },
        {
          "colorB": 228,
          "colorG": 176,
          "colorR": 74,
          "creationTime": 0,
          "name": "Placing + Crafting",
          "source": "",
          "type": "BuiltinCommonInstructions::Group",
          "events": [
            {
              "type": "BuiltinCommonInstructions::Standard",
              "conditions": [
                {
                  "type": {
                    "value": "CollisionNP"
                  },
                  "parameters": [
                    "Player",
                    "Crafting_Table",
                    "",
                    "",
                    ""
                  ]
                }
              ],
              "actions": [
                {
                  "type": {
                    "value": "MettreAutour"
                  },
                  "parameters": [
                    "Bolt",
                    "Crafting_Table",
                    "32",
                    "0"
                  ]
                },
                {
                  "type": {
                    "value": "MettreAutour"
                  },
                  "parameters": [
                    "Button2",
                    "Crafting_Table",
                    "32",
                    "90"
                  ]
                },
                {
                  "type": {
                    "value": "MettreAutour"
                  },
                  "parameters": [
                    "Spool",
                    "Crafting_Table",
                    "32",
                    "180"
                  ]
                },
                {
                  "type": {
                    "value": "SetBooleanVariable"
                  },
                  "parameters": [
                    "InvFull",
                    "False",
                    ""
                  ]
                }
              ]
            },
            {
              "type": "BuiltinCommonInstructions::Standard",
              "conditions": [
                {
                  "type": {
                    "value": "BooleanVariable"
                  },
                  "parameters": [
                    "HasBolt",
                    "=",
                    ""
                  ]
                },
                {
                  "type": {
                    "value": "BooleanVariable"
                  },
                  "parameters": [
                    "HasButton",
                    "=",
                    ""
                  ]
                },
                {
                  "type": {
                    "value": "BooleanVariable"
                  },
                  "parameters": [
                    "HasSpool",
                    "=",
                    ""
                  ]
                }
              ],
              "actions": [
                {
                  "type": {
                    "value": "SetBooleanVariable"
                  },
                  "parameters": [
                    "InvFull",
                    "False",
                    ""
                  ]
                }
              ]
            }
          ],
          "parameters": []
        }
      ],
      "layers": [
        {
          "ambientLightColorB": 200,
          "ambientLightColorG": 200,
          "ambientLightColorR": 200,
          "camera3DFarPlaneDistance": 10000,
          "camera3DFieldOfView": 45,
          "camera3DNearPlaneDistance": 3,
          "cameraType": "",
          "followBaseLayerCamera": false,
          "isLightingLayer": false,
          "isLocked": false,
          "name": "",
          "renderingType": "",
          "visibility": true,
          "cameras": [
            {
              "defaultSize": true,
              "defaultViewport": true,
              "height": 0,
              "viewportBottom": 1,
              "viewportLeft": 0,
              "viewportRight": 1,
              "viewportTop": 0,
              "width": 0
            }
          ],
          "effects": [
            {
              "effectType": "Scene3D::HemisphereLight",
              "name": "3D Light",
              "doubleParameters": {
                "elevation": 45,
                "intensity": 1,
                "rotation": 0
              },
              "stringParameters": {
                "groundColor": "64;64;64",
                "skyColor": "255;255;255",
                "top": "Y-"
              },
              "booleanParameters": {}
            }
          ]
        },
        {
          "ambientLightColorB": 200,
          "ambientLightColorG": 200,
          "ambientLightColorR": 200,
          "camera3DFarPlaneDistance": 10000,
          "camera3DFieldOfView": 45,
          "camera3DNearPlaneDistance": 3,
          "cameraType": "",
          "followBaseLayerCamera": false,
          "isLightingLayer": false,
          "isLocked": false,
          "name": "UI",
          "renderingType": "",
          "visibility": true,
          "cameras": [],
          "effects": [
            {
              "effectType": "Scene3D::HemisphereLight",
              "name": "3D Light",
              "doubleParameters": {
                "elevation": 45,
                "intensity": 1,
                "rotation": 0
              },
              "stringParameters": {
                "groundColor": "64;64;64",
                "skyColor": "255;255;255",
                "top": "Y-"
              },
              "booleanParameters": {}
            }
          ]
        }
      ],
      "behaviorsSharedData": [
        {
          "name": "Animation",
          "type": "AnimatableCapability::AnimatableBehavior"
        },
        {
          "name": "Effect",
          "type": "EffectCapability::EffectBehavior"
        },
        {
          "name": "Flippable",
          "type": "FlippableCapability::FlippableBehavior"
        },
        {
          "name": "Opacity",
          "type": "OpacityCapability::OpacityBehavior"
        },
        {
          "name": "Resizable",
          "type": "ResizableCapability::ResizableBehavior"
        },
        {
          "name": "Scale",
          "type": "ScalableCapability::ScalableBehavior"
        },
        {
          "name": "Text",
          "type": "TextContainerCapability::TextContainerBehavior"
        },
        {
          "name": "TopDownMovement",
          "type": "TopDownMovementBehavior::TopDownMovementBehavior"
        }
      ]
    }
  ],
  "externalEvents": [],
  "eventsFunctionsExtensions": [],
  "externalLayouts": [],
  "externalSourceFiles": []
}